{
  "id": "d24ae58a-17ea-40f9-9459-f904a00c38c8",
  "control_id": "12.9.1",
  "chunk": "PCI DSS 4_0_1 Requirement Control 12.9.1 Defined Approach Requirements: Additional requirement for service_ _providers only:_ TPSPs provide written agreements to customers that include acknowledgments that TPSPs are responsible for the security of account data the TPSP possesses or otherwise stores, processes, or transmits on behalf of the customer, or to the extent that the TPSP could impact the security of the customer\u2019s cardholder data and/or sensitive authentication data. Customized Approach Objective: TPSPs formally acknowledge their security responsibilities to their customers. Guidance: Purpose: In conjunction with requirement 12.8.2, this requirement is intended to promote a consistent level of understanding between tpsps and their customers about their applicable pci dss responsibilities. the acknowledgment from the tpsp evidences the tpsp\u2019s commitment to maintaining proper security of the account data that it obtains from its customers. the tpsp\u2019s internal policies and procedures related to their customer engagement process and any templates used for written agreements should include provision of an applicable pci dss acknowledgement to its customers. the method by which the tpsp provides written acknowledgment should be agreed between the provider and its customers.",
  "requirement": "Additional requirement for service_ _providers only:_ TPSPs provide written agreements to customers that include acknowledgments that TPSPs are responsible for the security of account data the TPSP possesses or otherwise stores, processes, or transmits on behalf of the customer, or to the extent that the TPSP could impact the security of the customer\u2019s cardholder data and/or sensitive authentication data.",
  "metadata": {
    "control_id": "12.9.1",
    "standard": "PCI-DSS-v4.0",
    "source": "PCI_DSS_PDF_v4.0",
    "control_category": "information_security_policy",
    "has_testing_procedures": false,
    "requirements_id": "12"
  }
}